pyspaceweather/__init__.py
pyspaceweather/pyspaceweather.py
pyspaceweather-0.1.0.dist-info/LICENSE
pyspaceweather-0.1.0.dist-info/METADATA
pyspaceweather-0.1.0.dist-info/WHEEL
pyspaceweather-0.1.0.dist-info/top_level.txt
pyspaceweather-0.1.0.dist-info/RECORD
