Metadata-Version: 2.1
Name: pyspaceweather
Version: 0.1.0
Summary: A Python wrapper for the Australian Bureau of Meteorology's Space Weather API.
Author-email: Ben Nour <hello@ben-nour.com>
License: MIT License
Project-URL: homepage, https://github.com/ben-n93/pyspaceweather
Project-URL: repository, https://github.com/ben-n93/pyspaceweather
Project-URL: documentation, https://py-spaceweather.readthedocs.io/en/latest/
Keywords: spaceweather,space,wrapper
Classifier: License :: OSI Approved :: MIT License
Classifier: Programming Language :: Python :: 3
Classifier: Programming Language :: Python :: 3.8
Classifier: Programming Language :: Python :: 3.9
Classifier: Programming Language :: Python :: 3.10
Classifier: Programming Language :: Python :: 3.11
Classifier: Programming Language :: Python :: 3.12
Requires-Python: >=3.8
License-File: LICENSE
Requires-Dist: requests ~=2.32.3
